dislocation/__init__.py
dislocation-0.0.0.dist-info/LICENSE
dislocation-0.0.0.dist-info/WHEEL
dislocation-0.0.0.dist-info/METADATA
dislocation-0.0.0.dist-info/RECORD
