Metadata-Version: 2.1
Name: dislocation
Version: 0.0.0
Summary: Library for dealing with dislocations.
License: MIT
Author: Dominik Steinberger
Author-email: dislocation@steinberger.io
Requires-Python: >=3.6,<4.0
Classifier: Development Status :: 1 - Planning
Classifier: Intended Audience :: Science/Research
Classifier: License :: OSI Approved :: MIT License
Classifier: Programming Language :: Python :: 3
Classifier: Programming Language :: Python :: 3.6
Classifier: Programming Language :: Python :: 3.7
Classifier: Topic :: Scientific/Engineering :: Physics
